pipeline_tool/__init__.py
pipeline_tool/blacklist.txt
pipeline_tool/constant.py
pipeline_tool/dataset.py
pipeline_tool/evaluate_mem.py
pipeline_tool/function_parser.py
pipeline_tool/gpu_alloc.py
pipeline_tool/pipeline_config.py
pipeline_tool/pipeline_tool.py
pipeline_tool/whitelist.txt
pipeline_tool/class_impl/CallFunction.py
pipeline_tool/class_impl/CallModule.py
pipeline_tool/class_impl/GetAttr.py
pipeline_tool/class_impl/GetAttrModule.py
pipeline_tool/class_impl/LayerClass.py
pipeline_tool/class_impl/PropagationLayer.py
pipeline_tool-0.0.2.dist-info/METADATA
pipeline_tool-0.0.2.dist-info/WHEEL
pipeline_tool-0.0.2.dist-info/licenses/LICENSE
pipeline_tool-0.0.2.dist-info/RECORD
