Metadata-Version: 2.1
Name: pipeline_tool
Version: 0.0.2
Summary: Alow splitting of big model in multiple GPU for training
Author-email: Bruno Da Rocha Carvalho <bruno.darochacarvalho@heig-vd.ch>, Gabriel Catel Torres Arzur <arzur.cateltorres@heig-vd.ch>
License:                     GNU AFFERO GENERAL PUBLIC LICENSE
License-File: LICENSE
Classifier: Environment :: GPU :: NVIDIA CUDA :: 12
Classifier: License :: OSI Approved :: GNU General Public License v3 (GPLv3)
Classifier: Natural Language :: English
Classifier: Operating System :: Unix
Classifier: Programming Language :: Python :: 3
Requires-Python: >=3.8
Requires-Dist: numpy<=1.23.3
Requires-Dist: torch<=1.13.1
Requires-Dist: torchvision<=0.14.1
